scikit_mol/__init__.py
scikit_mol/_constants.py
scikit_mol/_version.py
scikit_mol/conversions.py
scikit_mol/core.py
scikit_mol/descriptors.py
scikit_mol/parallel.py
scikit_mol/plotting.py
scikit_mol/safeinference.py
scikit_mol/standardizer.py
scikit_mol/utilities.py
scikit_mol/applicability/LICENSE.MIT
scikit_mol/applicability/README.md
scikit_mol/applicability/__init__.py
scikit_mol/applicability/base.py
scikit_mol/applicability/bounding_box.py
scikit_mol/applicability/convex_hull.py
scikit_mol/applicability/hotelling.py
scikit_mol/applicability/isolation_forest.py
scikit_mol/applicability/kernel_density.py
scikit_mol/applicability/knn.py
scikit_mol/applicability/leverage.py
scikit_mol/applicability/local_outlier.py
scikit_mol/applicability/mahalanobis.py
scikit_mol/applicability/standardization.py
scikit_mol/applicability/topkat.py
scikit_mol/fingerprints/__init__.py
scikit_mol/fingerprints/atompair.py
scikit_mol/fingerprints/avalon.py
scikit_mol/fingerprints/baseclasses.py
scikit_mol/fingerprints/maccs.py
scikit_mol/fingerprints/minhash.py
scikit_mol/fingerprints/morgan.py
scikit_mol/fingerprints/rdkitfp.py
scikit_mol/fingerprints/topologicaltorsion.py
scikit_mol-0.6.1.dist-info/METADATA
scikit_mol-0.6.1.dist-info/WHEEL
scikit_mol-0.6.1.dist-info/licenses/LICENSE
scikit_mol-0.6.1.dist-info/RECORD
