Metadata-Version: 2.4
Name: scikit-mol
Version: 0.6.1
Summary: scikit-learn classes for molecule transformation
Project-URL: Download, https://github.com/EBjerrum/scikit-mol
Project-URL: Homepage, https://github.com/EBjerrum/scikit-mol
Author-email: Esben Jannik Bjerrum <esben@cheminformania.com>
License-Expression: LGPL-3.0
License-File: LICENSE
Classifier: Development Status :: 3 - Alpha
Classifier: Intended Audience :: Science/Research
Classifier: License :: OSI Approved :: Apache Software License
Classifier: Operating System :: MacOS
Classifier: Operating System :: Microsoft :: Windows
Classifier: Operating System :: POSIX
Classifier: Operating System :: Unix
Classifier: Programming Language :: Python
Classifier: Programming Language :: Python :: 3 :: Only
Classifier: Programming Language :: Python :: 3.9
Classifier: Programming Language :: Python :: 3.10
Classifier: Programming Language :: Python :: 3.11
Classifier: Programming Language :: Python :: 3.12
Classifier: Topic :: Scientific/Engineering
Classifier: Topic :: Utilities
Requires-Python: <3.14,>=3.9
Requires-Dist: numpy
Requires-Dist: packaging
Requires-Dist: pandas
Requires-Dist: rdkit
Requires-Dist: scikit-learn
